[
  {
    "date": "2025-09-07",
    "eventTimestamp": "2025-09-07T04:00",
    "sport": "Fotbal",
    "league": "Spain: Primera Federacion 2025/2026",
    "event": "Osasuna B - Ourense CF",
    "createdByAdminId": "admin_global_001",
    "market": "Handicap 1 (0)",
    "selection": "Handicap 1 (0)",
    "odds": 2.2,
    "stake": 126.2,
    "id": "bet_1757253807934_c4e2728",
    "groupId": "grp_1757253807934_p5bpdjx",
    "betType": "VALUE",
    "status": "PENDING",
    "processedInDailyHistory": false,
    "notes": ""
  },
  {
    "date": "2025-09-07",
    "eventTimestamp": "2025-09-07T16:00",
    "sport": "Fotbal",
    "league": "Spain: Primera Federacion 2025/2026",
    "event": "Osasuna B - Ourense CF",
    "createdByAdminId": "admin_global_001",
    "market": "Handicap 2 (0)",
    "selection": "Handicap 2 (0)",
    "odds": 2.535,
    "stake": 146,
    "middleDetails": {
      "p1": 5.440000000000026,
      "p2": 97.91000000000001,
      "pb": 375.55000000000007
    },
    "id": "bet_1757253807934_r41xcpz",
    "groupId": "grp_1757253807934_p5bpdjx",
    "betType": "MIDDLE",
    "status": "PENDING",
    "processedInDailyHistory": false
  },
  {
    "date": "2025-09-07",
    "eventTimestamp": "2025-09-07T12:00",
    "sport": "Fotbal",
    "league": "Finland: Kolmonen 2025",
    "event": "PK 37 Iisalmi - SC Zulimanit",
    "createdByAdminId": "admin_global_001",
    "market": "Handicap 1 (-1.5)",
    "selection": "Handicap 1 (-1.5)",
    "odds": 2.222,
    "stake": 116.1,
    "id": "bet_1757246885417_0pbfe4v",
    "groupId": "grp_1757246885417_0eiowzd",
    "betType": "VALUE",
    "status": "VOID",
    "processedInDailyHistory": false,
    "notes": "Scor: 4-1.",
    "profit": 0,
    "resolvedAt": "2025-09-07T13:51:26.078Z"
  },
  {
    "date": "2025-09-07",
    "eventTimestamp": "2025-09-07T14:00",
    "sport": "Fotbal",
    "league": "Finland: Kolmonen 2025",
    "event": "PK 37 Iisalmi - SC Zulimanit",
    "createdByAdminId": "admin_global_001",
    "market": "Handicap 2 (+2.5)",
    "selection": "Handicap 2 (+2.5)",
    "odds": 2,
    "stake": 129,
    "middleDetails": {
      "p1": 12.874200000000002,
      "p2": 12.900000000000006,
      "pb": 270.8742
    },
    "id": "bet_1757246885417_xx3sptu",
    "groupId": "grp_1757246885417_0eiowzd",
    "betType": "MIDDLE",
    "status": "LOST",
    "processedInDailyHistory": false,
    "profit": -129,
    "resolvedAt": "2025-09-07T13:51:20.479Z"
  },
  {
    "date": "2025-09-07",
    "eventTimestamp": "2025-09-07T09:00",
    "sport": "Tenis",
    "league": "China: WTA 125K Huzhou 2025",
    "event": "Jessica Pieri - Eudice Wong Chong",
    "createdByAdminId": "admin_global_001",
    "market": "Sub 17.5 game-uri",
    "selection": "Sub 17.5 game-uri",
    "odds": 4.548,
    "stake": 10.85,
    "id": "bet_1757223057621_se6uwbs",
    "groupId": "grp_1757223057621_tgxvqwf",
    "betType": "VALUE",
    "status": "VOID",
    "processedInDailyHistory": false,
    "profit": 0,
    "resolvedAt": "2025-09-07T09:53:01.897Z",
    "notes": "Scor: 2-0."
  },
  {
    "date": "2025-09-07",
    "eventTimestamp": "2025-09-07T09:00",
    "sport": "Tenis",
    "league": "China: WTA 125K Huzhou 2025",
    "event": "Jessica Pieri - Eudice Wong Chong",
    "createdByAdminId": "admin_global_001",
    "market": "Handicap seturi 1 (-1.5)",
    "selection": "Handicap seturi 1 (-1.5)",
    "odds": 1.41,
    "stake": 35,
    "middleDetails": {
      "p1": 3.5,
      "p2": 3.5,
      "pb": 52.849999999999994
    },
    "id": "bet_1757223057621_6zmbtzo",
    "groupId": "grp_1757223057621_tgxvqwf",
    "betType": "MIDDLE",
    "status": "WON",
    "processedInDailyHistory": false,
    "profit": 14.349999999999998,
    "resolvedAt": "2025-09-07T09:52:48.023Z"
  },
  {
    "date": "2025-09-06",
    "eventTimestamp": "2025-09-07T00:30",
    "sport": "Baschet",
    "league": "LNB 2025",
    "event": "Ciudad Nueva - San Alfonzo ",
    "createdByAdminId": "admin_global_001",
    "market": "Peste 147.5",
    "selection": "Peste 147.5",
    "odds": 3.178,
    "stake": 22.73,
    "id": "bet_1757198334099_dghybwb",
    "groupId": "grp_1757198334099_xmwsjys",
    "betType": "VALUE",
    "status": "LOST",
    "processedInDailyHistory": true,
    "profit": -22.73,
    "resolvedAt": "2025-09-07T05:22:18.016Z",
    "notes": "Scor: 64-77."
  },
  {
    "date": "2025-09-06",
    "eventTimestamp": "2025-09-07T00:30",
    "sport": "Baschet",
    "league": "LNB 2025",
    "event": "Ciudad Nueva - San Alfonzo ",
    "createdByAdminId": "admin_global_001",
    "market": "Sub 151.5",
    "selection": "Sub 151.5",
    "odds": 1.605,
    "stake": 45,
    "middleDetails": {
      "p1": 4.5,
      "p2": 4.4999999999999964,
      "pb": 76.725
    },
    "id": "bet_1757198334099_lnoubti",
    "groupId": "grp_1757198334099_xmwsjys",
    "betType": "MIDDLE",
    "status": "WON",
    "processedInDailyHistory": true,
    "profit": 27.224999999999998,
    "resolvedAt": "2025-09-07T05:22:06.135Z"
  },
  {
    "date": "2025-09-07",
    "eventTimestamp": "2025-09-07T02:30",
    "sport": "Fotbal",
    "league": "United States: USA MLS 2025",
    "event": "Saint Louis City SC - FC Dallas ",
    "createdByAdminId": "admin_global_001",
    "market": "Handicap 1 (-1)",
    "selection": "Handicap 1 (-1)",
    "odds": 7.471,
    "stake": 7.65,
    "id": "bet_1757197204158_y3382kd",
    "groupId": "grp_1757197204158_q91y4qk",
    "betType": "VALUE",
    "status": "LOST",
    "processedInDailyHistory": false,
    "profit": -7.65,
    "resolvedAt": "2025-09-07T05:21:24.947Z",
    "notes": "Scor: 1-1."
  },
  {
    "date": "2025-09-07",
    "eventTimestamp": "2025-09-07T02:30",
    "sport": "Fotbal",
    "league": "United States: USA MLS 2025",
    "event": "Saint Louis City SC - FC Dallas ",
    "createdByAdminId": "admin_global_001",
    "market": "Handicap 2 (1,5)",
    "selection": "Handicap 2 (1,5)",
    "odds": 1.27,
    "stake": 45,
    "middleDetails": {
      "p1": 4.5,
      "p2": 4.5,
      "pb": 61.65
    },
    "id": "bet_1757197204158_s6eb2nv",
    "groupId": "grp_1757197204158_q91y4qk",
    "betType": "MIDDLE",
    "status": "WON",
    "processedInDailyHistory": false,
    "profit": 12.15,
    "resolvedAt": "2025-09-07T05:21:02.111Z"
  },
  {
    "date": "2025-09-06",
    "eventTimestamp": "2025-09-06T22:45",
    "sport": "Fotbal",
    "league": "Uruguay: Liga AUF Uruguaya - Clausura 2025",
    "event": "Penarol Montevideo - Plaza Colonia",
    "createdByAdminId": "admin_global_001",
    "market": "(Penarol Montevideo) - 1st Half",
    "selection": "(Penarol Montevideo) - 1st Half",
    "odds": 2.068,
    "stake": 79.31,
    "id": "bet_1757192728301_a56xk1y",
    "groupId": "grp_1757192728301_ansjdu9",
    "betType": "VALUE",
    "status": "LOST",
    "processedInDailyHistory": true,
    "profit": -79.31,
    "resolvedAt": "2025-09-06T22:09:31.799Z"
  },
  {
    "date": "2025-09-06",
    "eventTimestamp": "2025-09-06T22:45",
    "sport": "Fotbal",
    "league": "Uruguay: Liga AUF Uruguaya - Clausura 2025",
    "event": "Penarol Montevideo - Plaza Colonia",
    "createdByAdminId": "admin_global_001",
    "market": "Under 1.0 – 1st Half",
    "selection": "Under 1.0 – 1st Half",
    "odds": 2.13,
    "stake": 77,
    "middleDetails": {
      "p1": 7.700000000000017,
      "p2": 7.700000000000003,
      "pb": 171.71
    },
    "id": "bet_1757192728301_7zqwnko",
    "groupId": "grp_1757192728301_ansjdu9",
    "betType": "MIDDLE",
    "status": "WON",
    "processedInDailyHistory": true,
    "profit": 87.00999999999999,
    "resolvedAt": "2025-09-06T22:09:35.804Z",
    "notes": "Scor: 0-0."
  },
  {
    "date": "2025-09-06",
    "eventTimestamp": "2025-09-06T20:30",
    "sport": "Baschet",
    "league": "Friendly Club Matches 2024/2025",
    "event": "Dinamo Sassari - Bayern Munchen",
    "createdByAdminId": "admin_global_001",
    "market": "Handicap 1 (-1.5)",
    "selection": "Handicap 1 (-1.5)",
    "odds": 2.679,
    "stake": 42.57,
    "id": "bet_1757183689954_rp1vlg3",
    "groupId": "grp_1757183689954_hznkcej",
    "betType": "VALUE",
    "status": "VOID",
    "processedInDailyHistory": true,
    "profit": 0,
    "resolvedAt": "2025-09-06T20:42:23.081Z",
    "notes": "Scor: 86-89."
  },
  {
    "date": "2025-09-06",
    "eventTimestamp": "2025-09-06T20:30",
    "sport": "Baschet",
    "league": "Friendly Club Matches 2024/2025",
    "event": "Dinamo Sassari - Bayern Munchen",
    "createdByAdminId": "admin_global_001",
    "market": "Handicap 2 (2.5)",
    "selection": "Handicap 2 (2.5)",
    "odds": 1.755,
    "stake": 65,
    "middleDetails": {
      "p1": 6.5,
      "p2": 6.5,
      "pb": 120.57499999999999
    },
    "id": "bet_1757183689954_xqy76ye",
    "groupId": "grp_1757183689954_hznkcej",
    "betType": "MIDDLE",
    "status": "WON",
    "processedInDailyHistory": true,
    "profit": 49.074999999999996,
    "resolvedAt": "2025-09-06T20:42:17.971Z"
  },
  {
    "date": "2025-09-06",
    "eventTimestamp": "2025-09-06T16:45",
    "sport": "Fotbal",
    "league": "Spain: Tercera Division RFEF 2025/2026",
    "event": "Calvo Sotelo Puertollano - Albacete B",
    "createdByAdminId": "admin_global_001",
    "market": "Sub 2,5",
    "selection": "Sub 2,5",
    "odds": 2.2,
    "stake": 143,
    "id": "bet_1757178705366_89uitcs",
    "groupId": "grp_1757178705366_v2mvst7",
    "betType": "VALUE",
    "status": "LOST",
    "processedInDailyHistory": true,
    "notes": "",
    "profit": -143,
    "resolvedAt": "2025-09-06T18:13:54.009Z"
  },
  {
    "date": "2025-09-06",
    "eventTimestamp": "2025-09-06T18:45",
    "sport": "Fotbal",
    "league": "Spain: Tercera Division RFEF 2025/2026",
    "event": "Calvo Sotelo Puertollano - Albacete B",
    "createdByAdminId": "admin_global_001",
    "market": "Peste 2",
    "selection": "Peste 2",
    "odds": 2.045,
    "stake": 157,
    "middleDetails": {
      "p1": 14.600000000000023,
      "p2": 21.064999999999998,
      "pb": 335.665
    },
    "id": "bet_1757178705366_w6bxkgh",
    "groupId": "grp_1757178705366_v2mvst7",
    "betType": "MIDDLE",
    "status": "WON",
    "processedInDailyHistory": true,
    "profit": 164.065,
    "resolvedAt": "2025-09-06T18:14:02.552Z"
  },
  {
    "date": "2025-09-05",
    "eventTimestamp": "2025-09-05T20:00",
    "sport": "Fotbal",
    "league": "Campeonato Paulista U20 2024/2025",
    "event": "XV de Novembro (Piracicaba) U20 - Corinthians U20",
    "createdByAdminId": "admin_global_001",
    "market": "Under 3",
    "selection": "Under 3",
    "odds": 1.43,
    "stake": 161,
    "id": "bet_1757095447804_umc3xkm",
    "groupId": "grp_1757095447804_80310i1",
    "betType": "VALUE",
    "status": "WON",
    "processedInDailyHistory": true,
    "profit": 69.22999999999999,
    "resolvedAt": "2025-09-06T12:59:40.405Z",
    "notes": "Scor: 0-1."
  },
  {
    "date": "2025-09-05",
    "eventTimestamp": "2025-09-05T20:00",
    "sport": "Fotbal",
    "league": "Campeonato Paulista U20 2024/2025",
    "event": "XV de Novembro (Piracicaba) U20 - Corinthians U20",
    "createdByAdminId": "admin_global_001",
    "market": "Under 3",
    "selection": "Over 2.5",
    "odds": 4.333,
    "stake": 53.13,
    "middleDetails": {
      "p1": 16.1,
      "p2": 16.099999999999994,
      "pb": 246.32999999999998
    },
    "id": "bet_1757095447804_ccl2t0d",
    "groupId": "grp_1757095447804_80310i1",
    "betType": "MIDDLE",
    "status": "LOST",
    "processedInDailyHistory": true,
    "profit": -53.13,
    "resolvedAt": "2025-09-06T12:59:51.530Z"
  },
  {
    "date": "2025-09-05",
    "eventTimestamp": "2025-09-05T21:30",
    "sport": "Fotbal",
    "league": "Spain: LaLiga 2 2025/2026",
    "event": "Cordoba - Castellon",
    "createdByAdminId": "admin_global_001",
    "market": "Under 1.75 - 1st Half",
    "selection": "Under 1.75 - 1st Half",
    "odds": 1.32,
    "stake": 33,
    "id": "bet_1757095090296_4yvnj08",
    "groupId": "grp_1757095090295_m5c9brf",
    "betType": "VALUE",
    "status": "WON",
    "processedInDailyHistory": true,
    "profit": 10.560000000000002,
    "resolvedAt": "2025-09-06T13:00:30.943Z",
    "notes": "Scor: 0-1 - 1half."
  },
  {
    "date": "2025-09-05",
    "eventTimestamp": "2025-09-05T21:30",
    "sport": "Fotbal",
    "league": "Spain: LaLiga 2 2025/2026",
    "event": "Cordoba - Castellon",
    "createdByAdminId": "admin_global_001",
    "market": "Under 1.75 - 1st Half",
    "selection": "Over 1.25 – 1st Half",
    "odds": 6,
    "stake": 7.26,
    "middleDetails": {
      "p1": 3.3000000000000007,
      "p2": 3.299999999999997,
      "pb": 46.86
    },
    "id": "bet_1757095090296_gk0rkw1",
    "groupId": "grp_1757095090295_m5c9brf",
    "betType": "MIDDLE",
    "status": "VOID",
    "processedInDailyHistory": true,
    "profit": 0,
    "resolvedAt": "2025-09-06T13:02:17.192Z"
  },
  {
    "date": "2025-09-05",
    "eventTimestamp": "2025-09-05T19:30",
    "sport": "Fotbal",
    "league": "LaLiga 2 2025/2026",
    "event": "Albacete Balompie - CD Mirandes ",
    "createdByAdminId": "admin_global_001",
    "market": "Albacete Balompie",
    "selection": "Albacete Balompie",
    "odds": 1.795,
    "stake": 35,
    "id": "bet_1757093557875_2ldf4pp",
    "groupId": "grp_1757093557875_9y9us0y",
    "betType": "VALUE",
    "status": "LOST",
    "processedInDailyHistory": true,
    "profit": -35,
    "resolvedAt": "2025-09-06T13:02:37.410Z",
    "notes": "Scor: 1-4."
  },
  {
    "date": "2025-09-05",
    "eventTimestamp": "2025-09-05T19:30",
    "sport": "Fotbal",
    "league": "LaLiga 2 2025/2026",
    "event": "Albacete Balompie - CD Mirandes ",
    "createdByAdminId": "admin_global_001",
    "market": "Albacete Balompie",
    "selection": "X2",
    "odds": 2.583,
    "stake": 24.32,
    "middleDetails": {
      "p1": 3.5,
      "p2": 3.5,
      "pb": 66.32499999999999
    },
    "id": "bet_1757093557875_fw0xkp0",
    "groupId": "grp_1757093557875_9y9us0y",
    "betType": "MIDDLE",
    "status": "VOID",
    "processedInDailyHistory": true,
    "profit": 0,
    "resolvedAt": "2025-09-06T13:03:07.792Z"
  },
  {
    "date": "2025-09-05",
    "eventTimestamp": "2025-09-05T16:47",
    "sport": "Fotbal",
    "league": "FIFA World Cup Qualification - CONMEBOL 2023/2025",
    "event": "Paraguay - Ecuador ",
    "createdByAdminId": "admin_global_001",
    "market": "Under 2,5",
    "selection": "Under 2,5",
    "odds": 1.27,
    "stake": 59,
    "id": "bet_1757090920036_6otl4rn",
    "groupId": "grp_1757090920036_x7vu9zj",
    "betType": "VALUE",
    "status": "WON",
    "processedInDailyHistory": true,
    "profit": 15.930000000000001,
    "resolvedAt": "2025-09-05T16:48:50.472Z",
    "notes": "Scor: 0-0."
  },
  {
    "date": "2025-09-05",
    "eventTimestamp": "2025-09-05T16:47",
    "sport": "Fotbal",
    "league": "FIFA World Cup Qualification - CONMEBOL 2023/2025",
    "event": "Paraguay - Ecuador ",
    "createdByAdminId": "admin_global_001",
    "market": "Under 2,5",
    "selection": "Peste 2,5",
    "odds": 7.471,
    "stake": 10.03,
    "middleDetails": {
      "p1": 5.9,
      "p2": 5.900000000000006,
      "pb": 80.83000000000001
    },
    "id": "bet_1757090920036_q6wq677",
    "groupId": "grp_1757090920036_x7vu9zj",
    "betType": "MIDDLE",
    "status": "VOID",
    "processedInDailyHistory": true,
    "profit": 0,
    "resolvedAt": "2025-09-05T16:48:57.549Z"
  },
  {
    "date": "2025-09-03",
    "eventTimestamp": "2025-09-03T21:00",
    "sport": "Fotbal",
    "league": "Championship Women 2024/2025",
    "event": "Sion Swifts LFC (W) - Ballymena United (W)",
    "createdByAdminId": "admin_global_001",
    "market": "Over 4.5 ",
    "selection": "Over 4.5 ",
    "odds": 2,
    "stake": 65,
    "id": "bet_1756915652683_531v9jq",
    "groupId": "grp_1756915652682_2y2zbjo",
    "betType": "VALUE",
    "status": "LOST",
    "processedInDailyHistory": true,
    "profit": -65,
    "resolvedAt": "2025-09-04T15:27:56.970Z",
    "notes": "Scor: 2-0."
  },
  {
    "date": "2025-09-03",
    "eventTimestamp": "2025-09-03T21:00",
    "sport": "Fotbal",
    "league": "Championship Women 2024/2025",
    "event": "Sion Swifts LFC (W) - Ballymena United (W)",
    "createdByAdminId": "admin_global_001",
    "market": "Over 4.5 ",
    "selection": "Under 5.5 ",
    "odds": 2.222,
    "stake": 58.5,
    "middleDetails": {
      "p1": 6.500000000000007,
      "p2": 6.5,
      "pb": 136.5
    },
    "id": "bet_1756915652683_6hf5meb",
    "groupId": "grp_1756915652682_2y2zbjo",
    "betType": "MIDDLE",
    "status": "VOID",
    "processedInDailyHistory": true,
    "profit": 0,
    "resolvedAt": "2025-09-04T15:28:17.703Z"
  },
  {
    "date": "2025-09-03",
    "eventTimestamp": "2025-09-03T18:30",
    "sport": "Fotbal",
    "league": "Denmark Cup Women 2025/2026",
    "event": "Naestved HG (W) - Odense Q (W) ",
    "createdByAdminId": "admin_global_001",
    "market": "Under 3.5",
    "selection": "Under 3.5",
    "odds": 1.61,
    "stake": 126,
    "id": "bet_1756915124505_du20aia",
    "groupId": "grp_1756915124505_rg2b0b1",
    "betType": "VALUE",
    "status": "LOST",
    "processedInDailyHistory": true,
    "profit": -126,
    "resolvedAt": "2025-09-03T18:18:05.708Z",
    "notes": "Scor: 1-3."
  },
  {
    "date": "2025-09-03",
    "eventTimestamp": "2025-09-03T18:30",
    "sport": "Fotbal",
    "league": "Denmark Cup Women 2025/2026",
    "event": "Naestved HG (W) - Odense Q (W) ",
    "createdByAdminId": "admin_global_001",
    "market": "Under 3.5",
    "selection": "Over 2.5",
    "odds": 3.157,
    "stake": 64.26,
    "middleDetails": {
      "p1": 12.599999999999994,
      "p2": 12.599999999999994,
      "pb": 215.46
    },
    "id": "bet_1756915124505_dk5lp9k",
    "groupId": "grp_1756915124505_rg2b0b1",
    "betType": "MIDDLE",
    "status": "VOID",
    "processedInDailyHistory": true,
    "profit": 0,
    "resolvedAt": "2025-09-03T18:27:17.786Z"
  },
  {
    "date": "2025-09-03",
    "eventTimestamp": "2025-09-04T01:40",
    "sport": "Baseball",
    "league": "MLB 2025",
    "event": "Milwaukee Brewers - Philadelphia Phillies",
    "createdByAdminId": "admin_global_001",
    "market": "Over 8.5 ",
    "selection": "Over 8.5 ",
    "odds": 1.73,
    "stake": 36,
    "id": "bet_1756914910540_8fc97jf",
    "groupId": "grp_1756914910540_pd4lx3s",
    "betType": "VALUE",
    "status": "WON",
    "processedInDailyHistory": true,
    "profit": 26.28,
    "resolvedAt": "2025-09-04T15:28:41.415Z",
    "notes": "Scor: 6-3."
  },
  {
    "date": "2025-09-03",
    "eventTimestamp": "2025-09-04T01:40",
    "sport": "Baseball",
    "league": "MLB 2025",
    "event": "Milwaukee Brewers - Philadelphia Phillies",
    "createdByAdminId": "admin_global_001",
    "market": "Over 8.5 ",
    "selection": "Under 9.5 ",
    "odds": 2.746,
    "stake": 22.68,
    "middleDetails": {
      "p1": 3.6000000000000014,
      "p2": 3.6000000000000014,
      "pb": 65.88
    },
    "id": "bet_1756914910540_yhio241",
    "groupId": "grp_1756914910540_pd4lx3s",
    "betType": "MIDDLE",
    "status": "VOID",
    "processedInDailyHistory": true,
    "profit": 0,
    "resolvedAt": "2025-09-04T15:29:28.185Z"
  },
  {
    "date": "2025-09-03",
    "eventTimestamp": "2025-09-03T20:30",
    "sport": "Tenis",
    "league": "ATP Challenger Genoa 2025",
    "event": "Andrea Pellegrino - Nikolas Sanchez-Izquierdo ",
    "createdByAdminId": "admin_global_001",
    "market": "Game hcp +1.5 (Nikolas Sanchez-Izquierdo) ",
    "selection": "Game hcp +1.5 (Nikolas Sanchez-Izquierdo) ",
    "odds": 2.09,
    "stake": 31,
    "id": "bet_1756914464920_tbshq61",
    "groupId": "grp_1756914464919_9bpulkz",
    "betType": "VALUE",
    "status": "LOST",
    "processedInDailyHistory": true,
    "profit": -31,
    "resolvedAt": "2025-09-04T15:29:53.271Z",
    "notes": "Scor: 12-3."
  },
  {
    "date": "2025-09-03",
    "eventTimestamp": "2025-09-03T20:30",
    "sport": "Tenis",
    "league": "ATP Challenger Genoa 2025",
    "event": "Andrea Pellegrino - Nikolas Sanchez-Izquierdo ",
    "createdByAdminId": "admin_global_001",
    "market": "Game hcp +1.5 (Nikolas Sanchez-Izquierdo) ",
    "selection": "Game hcp -2.5 (Andrea Pellegrino)",
    "odds": 2.111,
    "stake": 30.69,
    "middleDetails": {
      "p1": 3.100000000000005,
      "p2": 3.1000000000000014,
      "pb": 67.88999999999999
    },
    "id": "bet_1756914464920_7pfcg78",
    "groupId": "grp_1756914464919_9bpulkz",
    "betType": "MIDDLE",
    "status": "VOID",
    "processedInDailyHistory": true,
    "profit": 0,
    "resolvedAt": "2025-09-04T15:30:33.439Z"
  },
  {
    "date": "2025-09-03",
    "eventTimestamp": "2025-09-03T20:00",
    "sport": "Fotbal",
    "league": "National Division 2025/2026",
    "event": "FC Mamer 32 - FC Differdange 03",
    "createdByAdminId": "admin_global_001",
    "market": "Over 3.5 ",
    "selection": "Over 3.5 ",
    "odds": 2.52,
    "stake": 43,
    "id": "bet_1756913756370_19bkl2x",
    "groupId": "grp_1756913756370_l6q87g6",
    "betType": "VALUE",
    "status": "WON",
    "processedInDailyHistory": true,
    "profit": 65.36,
    "resolvedAt": "2025-09-04T15:30:52.035Z",
    "notes": "Scor: 1-4."
  },
  {
    "date": "2025-09-03",
    "eventTimestamp": "2025-09-03T18:00",
    "sport": "Fotbal",
    "league": "National Division 2025/2026",
    "event": "FC Mamer 32 - FC Differdange 03",
    "createdByAdminId": "admin_global_001",
    "market": "Over 3.5 ",
    "selection": "Under 4.5 ",
    "odds": 1.775,
    "stake": 61.06,
    "middleDetails": {
      "p1": 4.299999999999997,
      "p2": 4.321499999999993,
      "pb": 112.6815
    },
    "id": "bet_1756913756370_mnvwnj9",
    "groupId": "grp_1756913756370_l6q87g6",
    "betType": "MIDDLE",
    "status": "VOID",
    "processedInDailyHistory": true,
    "notes": "",
    "profit": 0,
    "resolvedAt": "2025-09-04T15:31:17.358Z"
  },
  {
    "date": "2025-09-03",
    "eventTimestamp": "2025-09-03T18:30",
    "sport": "Fotbal",
    "league": "Copa Paraguay 2025",
    "event": "Sportivo San Lorenzo - Tacuary Asuncion",
    "createdByAdminId": "admin_global_001",
    "market": "Over 3.5 ",
    "selection": "Over 3.5 ",
    "odds": 2.875,
    "stake": 49,
    "id": "bet_1756913416717_9oopimb",
    "groupId": "grp_1756913416717_unq9jhf",
    "betType": "VALUE",
    "status": "LOST",
    "processedInDailyHistory": true,
    "profit": -49,
    "resolvedAt": "2025-09-03T18:40:25.078Z",
    "notes": "Scor: 1-1."
  },
  {
    "date": "2025-09-03",
    "eventTimestamp": "2025-09-03T18:30",
    "sport": "Fotbal",
    "league": "Copa Paraguay 2025",
    "event": "Sportivo San Lorenzo - Tacuary Asuncion",
    "createdByAdminId": "admin_global_001",
    "market": "Over 3.5 ",
    "selection": "Under 4.5",
    "odds": 1.62,
    "stake": 86.97,
    "middleDetails": {
      "p1": 4.900000000000006,
      "p2": 4.899999999999999,
      "pb": 145.775
    },
    "id": "bet_1756913416717_hmk6qeh",
    "groupId": "grp_1756913416717_unq9jhf",
    "betType": "MIDDLE",
    "status": "VOID",
    "processedInDailyHistory": true,
    "profit": 0,
    "resolvedAt": "2025-09-03T18:40:35.262Z"
  },
  {
    "date": "2025-09-03",
    "eventTimestamp": "2025-09-03T19:30",
    "sport": "Fotbal",
    "league": "Liga FUTVE 2 2025",
    "event": "Trujillanos FC - Falcon Heroes FC ",
    "createdByAdminId": "admin_global_001",
    "market": "Over 1.5 - 2nd Half ",
    "selection": "Over 1.5 - 2nd Half ",
    "odds": 2.03,
    "stake": 52,
    "id": "bet_1756913076391_1gtupvl",
    "groupId": "grp_1756913076390_xvahx89",
    "betType": "VALUE",
    "status": "WON",
    "processedInDailyHistory": true,
    "profit": 53.55999999999999,
    "resolvedAt": "2025-09-04T15:31:43.987Z",
    "notes": "Scor: 2-0 - 2half"
  },
  {
    "date": "2025-09-03",
    "eventTimestamp": "2025-09-03T19:30",
    "sport": "Fotbal",
    "league": "Liga FUTVE 2 2025",
    "event": "Trujillanos FC - Falcon Heroes FC ",
    "createdByAdminId": "admin_global_001",
    "market": "Over 1.5 - 2nd Half ",
    "selection": "Unde 2 - 2nd Half ",
    "odds": 2.183,
    "stake": 48.36,
    "middleDetails": {
      "p1": 5.199999999999989,
      "p2": 5.209879999999991,
      "pb": 110.76987999999997
    },
    "id": "bet_1756913076391_cxtatng",
    "groupId": "grp_1756913076390_xvahx89",
    "betType": "MIDDLE",
    "status": "VOID",
    "processedInDailyHistory": true,
    "notes": "",
    "profit": 0,
    "resolvedAt": "2025-09-04T15:32:41.850Z"
  },
  {
    "date": "2025-09-03",
    "eventTimestamp": "2025-09-03T19:10",
    "sport": "Baseball",
    "league": "MLB 2025",
    "event": "Detroit Tigers - New York Mets ",
    "createdByAdminId": "admin_global_001",
    "market": "Over 8.5",
    "selection": "Over 8.5",
    "odds": 1.75,
    "stake": 43,
    "id": "bet_1756912514403_wc31i88",
    "groupId": "grp_1756912514403_i0pfoao",
    "betType": "VALUE",
    "status": "LOST",
    "processedInDailyHistory": true,
    "profit": -43,
    "resolvedAt": "2025-09-04T15:33:04.496Z",
    "notes": "Scor: 6-2."
  },
  {
    "date": "2025-09-03",
    "eventTimestamp": "2025-09-03T19:10",
    "sport": "Baseball",
    "league": "MLB 2025",
    "event": "Detroit Tigers - New York Mets ",
    "createdByAdminId": "admin_global_001",
    "market": "Over 8.5",
    "selection": "Sub 9.5",
    "odds": 2.692,
    "stake": 27.95,
    "middleDetails": {
      "p1": 4.300000000000004,
      "p2": 4.299999999999997,
      "pb": 79.55
    },
    "id": "bet_1756912514403_vjz3zpd",
    "groupId": "grp_1756912514403_i0pfoao",
    "betType": "MIDDLE",
    "status": "VOID",
    "processedInDailyHistory": true,
    "profit": 0,
    "resolvedAt": "2025-09-04T15:33:34.379Z"
  },
  {
    "date": "2025-09-03",
    "eventTimestamp": "2025-09-03T18:00",
    "sport": "Fotbal",
    "league": "Finland: Kakkonen 2025",
    "event": "OsPa - TP 47 Tornio",
    "createdByAdminId": "admin_global_001",
    "market": "Asian hcp -1.5 (OsPa)",
    "selection": "Asian hcp -1.5 (OsPa)",
    "odds": 1.54,
    "stake": 140,
    "id": "bet_1756912269663_y9hlgwh",
    "groupId": "grp_1756912269663_9pcjyft",
    "betType": "VALUE",
    "status": "LOST",
    "processedInDailyHistory": true,
    "profit": -140,
    "resolvedAt": "2025-09-03T18:07:37.812Z",
    "notes": "Scor: 1-1."
  },
  {
    "date": "2025-09-03",
    "eventTimestamp": "2025-09-03T18:00",
    "sport": "Fotbal",
    "league": "Finland: Kakkonen 2025",
    "event": "OsPa - TP 47 Tornio",
    "createdByAdminId": "admin_global_001",
    "market": "Asian hcp -1.5 (OsPa)",
    "selection": "Asian hcp +2.5 (TP 47 Tornio)",
    "odds": 3.5,
    "stake": 61.6,
    "middleDetails": {
      "p1": 14,
      "p2": 14,
      "pb": 229.60000000000002
    },
    "id": "bet_1756912269663_g00vqwb",
    "groupId": "grp_1756912269663_9pcjyft",
    "betType": "MIDDLE",
    "status": "VOID",
    "processedInDailyHistory": true,
    "profit": 0,
    "resolvedAt": "2025-09-03T18:07:53.897Z"
  },
  {
    "date": "2025-09-02",
    "eventTimestamp": "2025-09-02T19:10",
    "sport": "Tenis",
    "league": "Mexico: WTA 125K Guadalajara 2025",
    "event": "Lucrezia Stefanini - Emiliana Arango",
    "createdByAdminId": "admin_global_001",
    "market": "Handicap asiatic +2.5 (Lucrezia Stefanini)",
    "selection": "Handicap asiatic +2.5 (Lucrezia Stefanini)",
    "odds": 1.755,
    "stake": 20,
    "id": "bet_1756833112927_3vt2h2j",
    "groupId": "grp_1756833112927_vt0ez6w",
    "betType": "VALUE",
    "status": "LOST",
    "processedInDailyHistory": true,
    "profit": -20,
    "resolvedAt": "2025-09-02T19:39:21.881Z",
    "notes": "Scor: 6-13."
  },
  {
    "date": "2025-09-02",
    "eventTimestamp": "2025-09-02T19:10",
    "sport": "Tenis",
    "league": "Mexico: WTA 125K Guadalajara 2025",
    "event": "Lucrezia Stefanini - Emiliana Arango",
    "createdByAdminId": "admin_global_001",
    "market": "Handicap asiatic +2.5 (Lucrezia Stefanini)",
    "selection": "Handicap asiatic -1.5 (Emiliana Arango)",
    "odds": 2.679,
    "stake": 13.1,
    "middleDetails": {
      "p1": 2.0000000000000018,
      "p2": 2,
      "pb": 37.099999999999994
    },
    "id": "bet_1756833112927_srqq7ri",
    "groupId": "grp_1756833112927_vt0ez6w",
    "betType": "MIDDLE",
    "status": "VOID",
    "processedInDailyHistory": true,
    "profit": 0,
    "resolvedAt": "2025-09-02T19:40:02.875Z"
  },
  {
    "date": "2025-09-02",
    "eventTimestamp": "2025-09-02T20:00",
    "sport": "Fotbal",
    "league": "England: EFL Trophy 2025/2026",
    "event": "Plymouth Argyle FC - Cheltenham Town - ",
    "createdByAdminId": "admin_global_001",
    "market": "Asian hcp -1.5 (Plymouth Argyle FC)",
    "selection": "Asian hcp -1.5 (Plymouth Argyle FC)",
    "odds": 2.02,
    "stake": 52,
    "id": "bet_1756832501429_wqgshjq",
    "groupId": "grp_1756832501428_dblnxkb",
    "betType": "VALUE",
    "status": "WON",
    "processedInDailyHistory": true,
    "profit": 53.04,
    "resolvedAt": "2025-09-02T19:56:26.142Z",
    "notes": "Scor: 2-0."
  },
  {
    "date": "2025-09-02",
    "eventTimestamp": "2025-09-02T18:00",
    "sport": "Fotbal",
    "league": "England: EFL Trophy 2025/2026",
    "event": "Plymouth Argyle FC - Cheltenham Town - ",
    "createdByAdminId": "admin_global_001",
    "market": "Asian hcp -1.5 (Plymouth Argyle FC)",
    "selection": "Asian hcp +2.5 (Cheltenham Town)",
    "odds": 2.84,
    "stake": 47.84,
    "middleDetails": {
      "p1": 5.199999999999996,
      "p2": 36.0256,
      "pb": 141.0656
    },
    "id": "bet_1756832501429_8zrfrco",
    "groupId": "grp_1756832501428_dblnxkb",
    "betType": "MIDDLE",
    "status": "WON",
    "processedInDailyHistory": true,
    "notes": "",
    "profit": 88.0256,
    "resolvedAt": "2025-09-02T19:56:50.171Z"
  },
  {
    "date": "2025-09-02",
    "eventTimestamp": "2025-09-02T19:00",
    "sport": "Tenis",
    "league": "US Open 2025",
    "event": "Jiri Lehecka - Carlos Alcaraz ",
    "createdByAdminId": "admin_global_001",
    "market": "Sub 30.5 game-uri",
    "selection": "Sub 30.5 game-uri",
    "odds": 2.17,
    "stake": 51,
    "id": "bet_1756831657035_21ybcbg",
    "groupId": "grp_1756831657035_4l6pdzb",
    "betType": "VALUE",
    "status": "WON",
    "processedInDailyHistory": true,
    "profit": 59.669999999999995,
    "resolvedAt": "2025-09-02T19:34:44.745Z",
    "notes": "Scor: 10-18."
  },
  {
    "date": "2025-09-02",
    "eventTimestamp": "2025-09-02T17:00",
    "sport": "Tenis",
    "league": "US Open 2025",
    "event": "Jiri Lehecka - Carlos Alcaraz ",
    "createdByAdminId": "admin_global_001",
    "market": "Sub 30.5 game-uri",
    "selection": "Peste 29.5 game-uri",
    "odds": 2.056,
    "stake": 54.57,
    "middleDetails": {
      "p1": 5.099999999999994,
      "p2": 6.625920000000001,
      "pb": 117.29592
    },
    "id": "bet_1756831657035_f8hhsf1",
    "groupId": "grp_1756831657035_4l6pdzb",
    "betType": "MIDDLE",
    "status": "LOST",
    "processedInDailyHistory": true,
    "notes": "",
    "profit": -54.57,
    "resolvedAt": "2025-09-02T19:35:55.693Z"
  },
  {
    "date": "2025-09-02",
    "eventTimestamp": "2025-09-02T20:45",
    "sport": "Fotbal",
    "league": "FA Cup 2025/2026",
    "event": "Prescot Cables - Hyde United FC",
    "createdByAdminId": "admin_global_001",
    "market": "Under 2.5 goluri",
    "selection": "Under 2.5 goluri",
    "odds": 2.24,
    "stake": 18,
    "id": "bet_1756831390767_yz0c6kf",
    "groupId": "grp_1756831390767_fmotj8o",
    "betType": "VALUE",
    "status": "WON",
    "processedInDailyHistory": true,
    "profit": 22.320000000000004,
    "resolvedAt": "2025-09-03T14:05:12.594Z",
    "notes": "Scor: 0-1."
  },
  {
    "date": "2025-09-02",
    "eventTimestamp": "2025-09-02T18:45",
    "sport": "Fotbal",
    "league": "FA Cup 2025/2026",
    "event": "Prescot Cables - Hyde United FC",
    "createdByAdminId": "admin_global_001",
    "market": "Under 2.5 goluri",
    "selection": "Peste 1.5 goluri",
    "odds": 1.984,
    "stake": 20.52,
    "middleDetails": {
      "p1": 1.8000000000000043,
      "p2": 2.191679999999998,
      "pb": 42.51168
    },
    "id": "bet_1756831390767_j1dr97i",
    "groupId": "grp_1756831390767_fmotj8o",
    "betType": "MIDDLE",
    "status": "LOST",
    "processedInDailyHistory": true,
    "notes": "",
    "profit": -20.52,
    "resolvedAt": "2025-09-03T14:05:46.063Z"
  },
  {
    "date": "2025-09-01",
    "eventTimestamp": "2025-09-01T20:15",
    "sport": "Baschet",
    "league": "EuroBasket 2025",
    "event": "Serbia - Czech Republic",
    "createdByAdminId": "admin_global_001",
    "market": "Asian hcp +25.5 (Czech Republic) ",
    "selection": "Asian hcp +25.5 (Czech Republic) ",
    "odds": 2.38,
    "stake": 71,
    "id": "bet_1756750856925_exfm3cv",
    "groupId": "grp_1756750856924_nzbv11v",
    "betType": "VALUE",
    "status": "WON",
    "processedInDailyHistory": true,
    "profit": 97.97999999999999,
    "resolvedAt": "2025-09-01T20:08:47.890Z",
    "notes": "Scor: 82-60."
  },
  {
    "date": "2025-09-01",
    "eventTimestamp": "2025-09-01T20:15",
    "sport": "Baschet",
    "league": "EuroBasket 2025",
    "event": "Serbia - Czech Republic",
    "createdByAdminId": "admin_global_001",
    "market": "Asian hcp +25.5 (Czech Republic) ",
    "selection": "Asian hcp -24.5 (Serbia) ",
    "odds": 1.859,
    "stake": 90.88,
    "middleDetails": {
      "p1": 7.099999999999994,
      "p2": 7.099999999999994,
      "pb": 176.07999999999998
    },
    "id": "bet_1756750856925_3vagdj8",
    "groupId": "grp_1756750856924_nzbv11v",
    "betType": "MIDDLE",
    "status": "LOST",
    "processedInDailyHistory": true,
    "profit": -90.88,
    "resolvedAt": "2025-09-01T20:09:13.672Z"
  },
  {
    "date": "2025-09-01",
    "eventTimestamp": "2025-09-01T18:30",
    "sport": "Tenis",
    "league": "United States: US Open 2025",
    "event": "Lorenzo Musetti - Jaume Antoni Munar Clar",
    "createdByAdminId": "admin_global_001",
    "market": "Under 8.5 - 1st Set",
    "selection": "Under 8.5 - 1st Set",
    "odds": 3.62,
    "stake": 25,
    "id": "bet_1756750465134_0w1vefy",
    "groupId": "grp_1756750465134_s9cj0u8",
    "betType": "VALUE",
    "status": "LOST",
    "processedInDailyHistory": true,
    "profit": -25,
    "resolvedAt": "2025-09-01T19:17:01.947Z",
    "notes": "Scor: 6-3 - 1st. Scor: 6-3 - 1st"
  },
  {
    "date": "2025-09-01",
    "eventTimestamp": "2025-09-01T20:30",
    "sport": "Tenis",
    "league": "United States: US Open 2025",
    "event": "Lorenzo Musetti - Jaume Antoni Munar Clar",
    "createdByAdminId": "admin_global_001",
    "market": "Under 8.5 - 1st Set",
    "selection": "Over 7.5 - 1st Set",
    "odds": 1.437,
    "stake": 63,
    "middleDetails": {
      "p1": 2.5,
      "p2": 2.5310000000000024,
      "pb": 93.031
    },
    "id": "bet_1756750465134_ylrj7ph",
    "groupId": "grp_1756750465134_s9cj0u8",
    "betType": "MIDDLE",
    "status": "VOID",
    "processedInDailyHistory": true,
    "profit": 0,
    "resolvedAt": "2025-09-01T19:17:25.609Z"
  },
  {
    "date": "2025-09-01",
    "eventTimestamp": "2025-09-01T22:10",
    "sport": "Baseball",
    "league": "United States: MLB 2025",
    "event": "Colorado Rockies - San Francisco Giants",
    "createdByAdminId": "admin_global_001",
    "market": "Asian hcp -2.5 (San Francisco Giants)",
    "selection": "Asian hcp -2.5 (San Francisco Giants)",
    "odds": 2.34,
    "stake": 23,
    "id": "bet_1756749965813_xxqkhv4",
    "groupId": "grp_1756749965813_nkk4cil",
    "betType": "VALUE",
    "status": "WON",
    "processedInDailyHistory": true,
    "profit": 30.819999999999997,
    "resolvedAt": "2025-09-02T16:32:57.513Z",
    "notes": "Scor: 2-8."
  },
  {
    "date": "2025-09-01",
    "eventTimestamp": "2025-09-01T22:10",
    "sport": "Baseball",
    "league": "United States: MLB 2025",
    "event": "Colorado Rockies - San Francisco Giants",
    "createdByAdminId": "admin_global_001",
    "market": "Asian hcp -2.5 (San Francisco Giants)",
    "selection": "Asian hcp +3 (Colorado Rockies)",
    "odds": 1.887,
    "stake": 28.52,
    "middleDetails": {
      "p1": 2.3000000000000007,
      "p2": 2.3000000000000007,
      "pb": 56.12
    },
    "id": "bet_1756749965813_8z9bzz4",
    "groupId": "grp_1756749965813_nkk4cil",
    "betType": "MIDDLE",
    "status": "VOID",
    "processedInDailyHistory": true,
    "profit": 0,
    "resolvedAt": "2025-09-02T16:33:41.898Z"
  },
  {
    "date": "2025-09-01",
    "eventTimestamp": "2025-09-02T01:35",
    "sport": "Baseball",
    "league": "MLB 2025",
    "event": "Tampa Bay Rays - Seattle Mariners ",
    "createdByAdminId": "admin_global_001",
    "market": "Asian hcp -1 (Tampa Bay Rays) ",
    "selection": "Asian hcp -1 (Tampa Bay Rays) ",
    "odds": 2.32,
    "stake": 25,
    "id": "bet_1756749163494_lxxb01f",
    "groupId": "grp_1756749163494_cfdg2nf",
    "betType": "VALUE",
    "status": "WON",
    "processedInDailyHistory": true,
    "profit": 32.99999999999999,
    "resolvedAt": "2025-09-02T16:33:58.456Z",
    "notes": "Scor: 10-2."
  },
  {
    "date": "2025-09-01",
    "eventTimestamp": "2025-09-01T23:35",
    "sport": "Baseball",
    "league": "MLB 2025",
    "event": "Tampa Bay Rays - Seattle Mariners ",
    "createdByAdminId": "admin_global_001",
    "market": "Asian hcp -1 (Tampa Bay Rays) ",
    "selection": "Asian hcp +1.5 (Seattle Mariners)",
    "odds": 1.902,
    "stake": 30.5,
    "middleDetails": {
      "p1": 2.499999999999993,
      "p2": 2.5109999999999957,
      "pb": 60.51099999999999
    },
    "id": "bet_1756749163494_a0bdl4m",
    "groupId": "grp_1756749163494_cfdg2nf",
    "betType": "MIDDLE",
    "status": "VOID",
    "processedInDailyHistory": true,
    "notes": "",
    "profit": 0,
    "resolvedAt": "2025-09-02T16:34:20.454Z"
  },
  {
    "date": "2025-09-01",
    "eventTimestamp": "2025-09-01T02:00",
    "sport": "Tenis",
    "league": "United States: US Open 2025",
    "event": "Novak Djokovic - Jan Lennard Struff",
    "createdByAdminId": "admin_global_001",
    "market": "Game hcp -6.5 (Novak Djokovic)",
    "selection": "Game hcp -6.5 (Novak Djokovic)",
    "odds": 2.04,
    "stake": 31,
    "id": "bet_1756679164461_heksc7r",
    "groupId": "grp_1756679164460_4n053rz",
    "betType": "VALUE",
    "status": "WON",
    "processedInDailyHistory": true,
    "profit": 32.24,
    "resolvedAt": "2025-09-01T14:33:52.074Z",
    "notes": "Scor: 18-8 Game-uri."
  },
  {
    "date": "2025-09-01",
    "eventTimestamp": "2025-09-01T02:00",
    "sport": "Tenis",
    "league": "United States: US Open 2025",
    "event": "Novak Djokovic - Jan Lennard Struff",
    "createdByAdminId": "admin_global_001",
    "market": "Game hcp -6.5 (Novak Djokovic)",
    "selection": "Game hcp +7.5 (Jan Lennard Struff)",
    "odds": 2.17,
    "stake": 29.14,
    "middleDetails": {
      "p1": 3.1000000000000085,
      "p2": 3.1000000000000014,
      "pb": 66.34
    },
    "id": "bet_1756679164461_4canbe9",
    "groupId": "grp_1756679164460_4n053rz",
    "betType": "MIDDLE",
    "status": "VOID",
    "processedInDailyHistory": true,
    "profit": 0,
    "resolvedAt": "2025-09-01T14:34:36.795Z"
  },
  {
    "date": "2025-08-31",
    "eventTimestamp": "2025-09-01T01:30",
    "sport": "Fotbal",
    "league": "Serie A 2025",
    "event": "SC Internacional RS - Fortaleza CE",
    "createdByAdminId": "admin_global_001",
    "market": "Asian hcp +1 (Fortaleza CE)",
    "selection": "Asian hcp +1 (Fortaleza CE)",
    "odds": 1.69,
    "stake": 7,
    "id": "bet_1756677189826_z3sn4ke",
    "groupId": "grp_1756677189826_ir3e0bl",
    "betType": "VALUE",
    "status": "VOID",
    "processedInDailyHistory": false,
    "profit": 0,
    "resolvedAt": "2025-09-01T14:32:39.854Z",
    "notes": "Scor: 2-1."
  },
  {
    "date": "2025-08-31",
    "eventTimestamp": "2025-09-01T01:30",
    "sport": "Fotbal",
    "league": "Serie A 2025",
    "event": "SC Internacional RS - Fortaleza CE",
    "createdByAdminId": "admin_global_001",
    "market": "Asian hcp +1 (Fortaleza CE)",
    "selection": "Asian hcp -1 (SC Internacional RS)",
    "odds": 2.864,
    "stake": 4.13,
    "middleDetails": {
      "p1": 0.7000000000000011,
      "p2": 0.6999999999999993,
      "pb": 12.53
    },
    "id": "bet_1756677189826_9dwoz89",
    "groupId": "grp_1756677189826_ir3e0bl",
    "betType": "MIDDLE",
    "status": "VOID",
    "processedInDailyHistory": false,
    "profit": 0,
    "resolvedAt": "2025-09-01T14:33:17.101Z"
  },
  {
    "date": "2025-08-31",
    "eventTimestamp": "2025-08-31T21:30",
    "sport": "Fotbal",
    "league": "Primeira Liga 2025/2026",
    "event": "Santa Clara - Estrela Amadora",
    "createdByAdminId": "admin_global_001",
    "market": "Sub 1.5 goluri",
    "selection": "Sub 1.5 goluri",
    "odds": 2.185,
    "stake": 10,
    "id": "bet_1756668062106_nctpq8r",
    "groupId": "grp_1756668062106_x8jasvc",
    "betType": "VALUE",
    "status": "WON",
    "processedInDailyHistory": true,
    "profit": 11.850000000000001,
    "resolvedAt": "2025-08-31T21:36:38.848Z",
    "notes": "Scor: 0-0."
  },
  {
    "date": "2025-08-31",
    "eventTimestamp": "2025-08-31T21:30",
    "sport": "Fotbal",
    "league": "Primeira Liga 2025/2026",
    "event": "Santa Clara - Estrela Amadora",
    "createdByAdminId": "admin_global_001",
    "market": "Sub 1.5 goluri",
    "selection": "Peste 0.5 goluri",
    "odds": 2.014,
    "stake": 10.85,
    "middleDetails": {
      "p1": 1,
      "p2": 0.9999999999999964,
      "pb": 22.849999999999998
    },
    "id": "bet_1756668062106_133wfcz",
    "groupId": "grp_1756668062106_x8jasvc",
    "betType": "MIDDLE",
    "status": "LOST",
    "processedInDailyHistory": true,
    "profit": -10.85,
    "resolvedAt": "2025-08-31T21:36:53.057Z",
    "notes": "Scor: 0-0."
  },
  {
    "date": "2025-08-31",
    "sport": "Fotbal",
    "league": "3.SNL 2025/2026",
    "event": "NK Smartno - NK Carda ",
    "createdByAdminId": "admin_global_001",
    "market": "Peste 3 goluri",
    "selection": "Peste 3 goluri",
    "odds": 1.58,
    "stake": 46,
    "id": "bet_1756652640608_qewcct6",
    "groupId": "grp_1756652640608_qwfgraz",
    "betType": "VALUE",
    "status": "VOID",
    "processedInDailyHistory": true,
    "eventTimestamp": "2025-08-31T17:00",
    "notes": "Scor: 2 - 1.",
    "profit": 0,
    "resolvedAt": "2025-08-31T17:00:14.186Z"
  },
  {
    "date": "2025-08-31",
    "sport": "Fotbal",
    "league": "3.SNL 2025/2026",
    "event": "NK Smartno - NK Carda ",
    "createdByAdminId": "admin_global_001",
    "market": "Peste 3 goluri",
    "selection": "Sub 3.5 goluri",
    "odds": 3.6,
    "stake": 22.08,
    "middleDetails": {
      "p1": 4.600000000000005,
      "p2": 11.407999999999994,
      "pb": 84.088
    },
    "id": "bet_1756652640608_qyc7vu4",
    "groupId": "grp_1756652640608_qwfgraz",
    "betType": "MIDDLE",
    "status": "WON",
    "processedInDailyHistory": true,
    "eventTimestamp": "2025-08-31T15:00",
    "notes": "",
    "profit": 57.407999999999994,
    "resolvedAt": "2025-08-31T17:00:17.469Z"
  },
  {
    "date": "2025-08-31",
    "sport": "Fotbal",
    "league": "Serie A 2025/2026",
    "event": "SS Lazio - Hellas Verona ",
    "createdByAdminId": "admin_global_001",
    "market": "Sub 1.5 goluri",
    "selection": "Sub 1.5 goluri",
    "odds": 2.95,
    "stake": 16,
    "id": "bet_1756652386243_e2tkbzg",
    "groupId": "grp_1756652386243_21z4gop",
    "betType": "VALUE",
    "status": "LOST",
    "processedInDailyHistory": true,
    "profit": -16,
    "resolvedAt": "2025-08-31T18:58:47.075Z"
  },
  {
    "date": "2025-08-31",
    "sport": "Fotbal",
    "league": "Serie A 2025/2026",
    "event": "SS Lazio - Hellas Verona ",
    "createdByAdminId": "admin_global_001",
    "market": "Sub 1.5 goluri",
    "selection": "Peste 0.5 goluri",
    "odds": 1.595,
    "stake": 29.6,
    "middleDetails": {
      "p1": 1.6000000000000085,
      "p2": 1.6000000000000014,
      "pb": 48.800000000000004
    },
    "id": "bet_1756652386243_q0mqv74",
    "groupId": "grp_1756652386243_21z4gop",
    "betType": "MIDDLE",
    "status": "VOID",
    "processedInDailyHistory": true,
    "profit": 0,
    "resolvedAt": "2025-08-31T18:58:53.680Z"
  },
  {
    "date": "2025-08-30",
    "sport": "Fotbal",
    "league": "Premier League 2025/2026",
    "event": "Akron Tolyatti - FK Baltika Kaliningrad ",
    "createdByAdminId": "admin_global_001",
    "market": "1x2 (FK Baltika Kaliningrad) - Ordinary Time",
    "selection": "1x2 (FK Baltika Kaliningrad) - Ordinary Time",
    "odds": 2.3,
    "stake": 19,
    "id": "bet_1756589567639_pfd0diq",
    "groupId": "grp_1756589567639_kimyhry",
    "betType": "VALUE",
    "status": "VOID",
    "processedInDailyHistory": true,
    "profit": 0,
    "resolvedAt": "2025-08-31T13:47:06.294Z"
  },
  {
    "date": "2025-08-30",
    "sport": "Fotbal",
    "league": "Premier League 2025/2026",
    "event": "Akron Tolyatti - FK Baltika Kaliningrad ",
    "createdByAdminId": "admin_global_001",
    "market": "1x2 (FK Baltika Kaliningrad) - Ordinary Time",
    "selection": "Handicap +1.5 (Akron Tolyatti)",
    "odds": 1.917,
    "stake": 22.8,
    "middleDetails": {
      "p1": 1.8999999999999986,
      "p2": 1.8999999999999986,
      "pb": 45.599999999999994
    },
    "id": "bet_1756589567639_gq2nc06",
    "groupId": "grp_1756589567639_kimyhry",
    "betType": "MIDDLE",
    "status": "VOID",
    "processedInDailyHistory": true,
    "profit": 0,
    "resolvedAt": "2025-08-31T13:47:09.301Z"
  },
  {
    "date": "2025-08-30",
    "sport": "Tenis",
    "league": "Liga Prom 2025/2026",
    "event": "Herrera Reserves - Udelas FC",
    "createdByAdminId": "admin_global_001",
    "market": "Asian hcp +0.25 (Herrera Reserves) - Ordinary Time",
    "selection": "Asian hcp +0.25 (Herrera Reserves) - Ordinary Time",
    "odds": 2.3,
    "stake": 26,
    "id": "bet_1756587110523_jwu2315",
    "groupId": "grp_1756587110523_v0dyko8",
    "betType": "VALUE",
    "status": "VOID",
    "processedInDailyHistory": true,
    "profit": 0,
    "resolvedAt": "2025-08-31T04:13:37.904Z"
  },
  {
    "date": "2025-08-30",
    "sport": "Tenis",
    "league": "Liga Prom 2025/2026",
    "event": "Herrera Reserves - Udelas FC",
    "createdByAdminId": "admin_global_001",
    "market": "Asian hcp +0.25 (Herrera Reserves) - Ordinary Time",
    "selection": "Asian hcp +1.5 (Udelas FC)",
    "odds": 1.917,
    "stake": 31.2,
    "middleDetails": {
      "p1": 2.600000000000005,
      "p2": 2.6000000000000014,
      "pb": 62.4
    },
    "id": "bet_1756587110523_ob0u1ln",
    "groupId": "grp_1756587110523_v0dyko8",
    "betType": "MIDDLE",
    "status": "VOID",
    "processedInDailyHistory": true,
    "profit": 0,
    "resolvedAt": "2025-08-31T04:07:35.938Z"
  },
  {
    "date": "2025-08-30",
    "sport": "Tenis",
    "league": "United States: US Open 2025",
    "event": "Daniel Altmaier vs Alex De Minaur",
    "createdByAdminId": "admin_global_001",
    "market": "Total game-uri",
    "selection": "Under 30.5",
    "odds": 1.97,
    "stake": 8,
    "id": "bet_1756583449119_olfu45g",
    "groupId": "grp_1756583449119_yl18iuw",
    "betType": "VALUE",
    "status": "LOST",
    "processedInDailyHistory": true,
    "notes": "",
    "profit": -8,
    "resolvedAt": "2025-08-31T04:10:38.026Z"
  },
  {
    "date": "2025-08-30",
    "sport": "Tenis",
    "league": "United States: US Open 2025",
    "event": "Daniel Altmaier vsAlex De Minaur",
    "createdByAdminId": "admin_global_001",
    "market": "Total game-uri",
    "selection": "Over 30",
    "odds": 2.364,
    "stake": 6.45,
    "middleDetails": {
      "p1": 1.310126368997472,
      "p2": 0.8000000000000007,
      "pb": 16.560000000000002
    },
    "id": "bet_1756583449119_ws853xm",
    "groupId": "grp_1756583449119_yl18iuw",
    "betType": "MIDDLE",
    "status": "VOID",
    "processedInDailyHistory": true,
    "profit": 0,
    "resolvedAt": "2025-08-31T04:11:50.255Z"
  },
  {
    "date": "2025-08-30",
    "sport": "Fotbal",
    "league": "Australia: Northern NSW Reserves League 2025",
    "event": "Newcastle Olympic Reserves vs Cooks Hill United FC Reserves",
    "createdByAdminId": "admin_global_001",
    "market": "Asian handicap",
    "selection": "Asian hcp +1 (Cooks Hill United FC Reserves)",
    "odds": 1.8,
    "stake": 53,
    "id": "bet_1756583140225_y232ge7",
    "groupId": "grp_1756583140224_5x1at5l",
    "betType": "VALUE",
    "status": "WON",
    "processedInDailyHistory": true,
    "profit": 42.400000000000006,
    "resolvedAt": "2025-08-31T04:09:51.448Z"
  },
  {
    "date": "2025-08-30",
    "sport": "Fotbal",
    "league": "Australia: Northern NSW Reserves League 2025",
    "event": "Newcastle Olympic Reserves vs Cooks Hill United FC Reserves",
    "createdByAdminId": "admin_global_001",
    "market": "Asian handicap",
    "selection": "Sub 3.5 goluri",
    "odds": 2.625,
    "stake": 37.1,
    "middleDetails": {
      "p1": 5.300000000000004,
      "p2": 5.29999999999999,
      "pb": 100.69999999999999
    },
    "id": "bet_1756583140225_sjj7zne",
    "groupId": "grp_1756583140224_5x1at5l",
    "betType": "MIDDLE",
    "status": "WON",
    "processedInDailyHistory": true,
    "profit": 60.2875,
    "resolvedAt": "2025-08-31T04:09:57.114Z",
    "notes": ""
  }
]
